jupyter_docprovider_codio/__init__.py
jupyter_docprovider_codio/_version.py
jupyter_docprovider_codio-2.1.1.data/data/share/jupyter/labextensions/docprovider-extension-codio/package.json
jupyter_docprovider_codio-2.1.1.data/data/share/jupyter/labextensions/docprovider-extension-codio/static/20.114e91c3e854ad17cf2c.js
jupyter_docprovider_codio-2.1.1.data/data/share/jupyter/labextensions/docprovider-extension-codio/static/422.6b0e09d1345a6bf6e1ea.js
jupyter_docprovider_codio-2.1.1.data/data/share/jupyter/labextensions/docprovider-extension-codio/static/444.bdfc2c5249d9bfe47b0e.js
jupyter_docprovider_codio-2.1.1.data/data/share/jupyter/labextensions/docprovider-extension-codio/static/840.33666aef8ec77264e958.js
jupyter_docprovider_codio-2.1.1.data/data/share/jupyter/labextensions/docprovider-extension-codio/static/944.be7235c91f0dc005aaa4.js
jupyter_docprovider_codio-2.1.1.data/data/share/jupyter/labextensions/docprovider-extension-codio/static/96.947875594fd1250b2ad1.js
jupyter_docprovider_codio-2.1.1.data/data/share/jupyter/labextensions/docprovider-extension-codio/static/remoteEntry.2c320ffe8bdfc52130c7.js
jupyter_docprovider_codio-2.1.1.data/data/share/jupyter/labextensions/docprovider-extension-codio/static/style.js
jupyter_docprovider_codio-2.1.1.data/data/share/jupyter/labextensions/docprovider-extension-codio/static/third-party-licenses.json
jupyter_docprovider_codio-2.1.1.data/data/share/jupyter/labextensions/docprovider-extension-codio/install.json
jupyter_docprovider_codio-2.1.1.dist-info/METADATA
jupyter_docprovider_codio-2.1.1.dist-info/WHEEL
jupyter_docprovider_codio-2.1.1.dist-info/licenses/LICENSE
jupyter_docprovider_codio-2.1.1.dist-info/RECORD
